pyparadigm/__init__.py
pyparadigm/_primitives.py
pyparadigm/dialogs.py
pyparadigm/eventlistener.py
pyparadigm/extras.py
pyparadigm/misc.py
pyparadigm/surface_composition.py
pyparadigm-1.2.2.dist-info/LICENSE
pyparadigm-1.2.2.dist-info/WHEEL
pyparadigm-1.2.2.dist-info/METADATA
pyparadigm-1.2.2.dist-info/RECORD
