Metadata-Version: 2.1
Name: pyparadigm
Version: 1.2.2
Summary: A package to build psychological Paradigms. Based on PyGame 
Home-page: https://github.com/KnorrFG/pyparadigm
Author: Felix G. Knorr
Author-email: knorr.felix@gmx.de
Requires-Python: >=3.5
Classifier: License :: OSI Approved :: MIT License
Classifier: Programming Language :: Python :: 3
Requires-Dist: pygame (>=1.9.3)
